dynamic_models/activity_base.py
dynamic_models/auto_heart_beat.py
dynamic_models/helper.py
dynamic_models/workflow_input.py
dynamic_temporal_models-0.2.16.dist-info/METADATA
dynamic_temporal_models-0.2.16.dist-info/WHEEL
dynamic_temporal_models-0.2.16.dist-info/top_level.txt
dynamic_temporal_models-0.2.16.dist-info/RECORD
