Metadata-Version: 2.4
Name: dynamic-temporal-models
Version: 0.2.16
Summary: A package for managing dynamic workflows and activities using Temporal.
Author-email: Tai Nguyen <tainguyen.ntt.97@gmail.com>
License: MIT
Classifier: Programming Language :: Python :: 3
Classifier: Operating System :: OS Independent
Requires-Python: >=3.8
